checker/__init__.py
checker/src/__init__.py
checker/src/constants.py
checker/src/helper.py
checker/src/cmd/__init__.py
checker/src/cmd/main.py
malsabbagh_checker_multiple_two-0.2.0.data/scripts/doc-as-code
tests/__init__.py
malsabbagh_checker_multiple_two-0.2.0.dist-info/METADATA
malsabbagh_checker_multiple_two-0.2.0.dist-info/WHEEL
malsabbagh_checker_multiple_two-0.2.0.dist-info/top_level.txt
malsabbagh_checker_multiple_two-0.2.0.dist-info/RECORD
