Metadata-Version: 2.1
Name: malsabbagh-checker-multiple-two
Version: 0.2.0
Summary: Python links checker
Home-page: UNKNOWN
Author: Mohamed
Author-email: UNKNOWN
License: MIT
Platform: UNKNOWN
